siso/__init__.py
siso/__main__.py
siso/api.py
siso/coord.py
siso/impl.py
siso/instrument.py
siso/multisource.py
siso/topology.py
siso/types.py
siso/filter/__init__.py
siso/filter/basis_filter.py
siso/filter/basismerge.py
siso/filter/coordtransform.py
siso/filter/decompose.py
siso/filter/discretize.py
siso/filter/eigendisp.py
siso/filter/field_filter.py
siso/filter/force_unstructured.py
siso/filter/keyzones.py
siso/filter/passthrough.py
siso/filter/recombine.py
siso/filter/strict.py
siso/filter/timeslice.py
siso/filter/zonemerge.py
siso/reader/__init__.py
siso/reader/gotools.py
siso/reader/ifem.py
siso/reader/lrspline.py
siso/reader/nastran.py
siso/reader/puregeometry.py
siso/reader/simra.py
siso/reader/wrf.py
siso/util/__init__.py
siso/util/bisect.py
siso/util/cell_numbering.py
siso/util/coord.py
siso/util/field_data.py
siso/writer/__init__.py
siso/writer/api.py
siso/writer/simra.py
siso/writer/vtf.py
siso/writer/vtk.py
siso-4.3.0.dist-info/METADATA
siso-4.3.0.dist-info/WHEEL
siso-4.3.0.dist-info/entry_points.txt
siso-4.3.0.dist-info/licenses/LICENSE
siso-4.3.0.dist-info/RECORD
