Metadata-Version: 2.4
Name: siso
Version: 4.3.0
Author-email: Eivind Fonn <eivind.fonn@sintef.no>
License-File: LICENSE
Requires-Python: <4.0,>=3.12
Requires-Dist: attrs<26.0.0,>=25.0.0
Requires-Dist: click-option-group<1.0.0,>=0.5.5
Requires-Dist: click==8.1.3
Requires-Dist: f90nml<2.0.0,>=1.4.3
Requires-Dist: h5py<4.0.0,>=3.8.0
Requires-Dist: jax<1.0.0,>=0.4.6
Requires-Dist: jaxlib<1.0.0,>=0.4.6
Requires-Dist: lrspline>=1.15.1
Requires-Dist: more-itertools>=10.2.0
Requires-Dist: netcdf4<2.0.0,>=1.7.2
Requires-Dist: numpy<3.0.0,>=2.0.0
Requires-Dist: pyerfa<3.0.0.0,>=2.0.0.1
Requires-Dist: rich<15.0.0,>=14.0.0
Requires-Dist: splipy<2.0.0,>=1.7.0
Requires-Dist: vtk<10.0.0,>=9.2.5
Provides-Extra: vtf
Requires-Dist: vtfwriter; extra == 'vtf'
